fair_wizard/__init__.py
fair_wizard/automation/__init__.py
fair_wizard/automation/common/__init__.py
fair_wizard/automation/common/model.py
fair_wizard/automation/common/wrappers.py
fair_wizard/automation/openid/__init__.py
fair_wizard/automation/openid/handlers.py
fair_wizard/automation/openid/model.py
fair_wizard/automation/openid/wrappers.py
fair_wizard/automation/saml/__init__.py
fair_wizard/automation/saml/handlers.py
fair_wizard/automation/saml/helpers.py
fair_wizard/automation/saml/model.py
fair_wizard/automation/saml/wrappers.py
fair_wizard_integration_sdk-1.0.0.dist-info/LICENSE
fair_wizard_integration_sdk-1.0.0.dist-info/METADATA
fair_wizard_integration_sdk-1.0.0.dist-info/WHEEL
fair_wizard_integration_sdk-1.0.0.dist-info/top_level.txt
fair_wizard_integration_sdk-1.0.0.dist-info/RECORD
