Metadata-Version: 2.1
Name: fair-wizard-integration-sdk
Version: 1.0.0
Summary: Python SDK for building integrations with FAIR Wizard
Author-email: Vojtěch Knaisl <vojtech.knaisl@fair-wizard.com>, Marek Suchánek <marek.suchanek@fair-wizard.com>
Project-URL: Homepage, https://fair-wizard.com
Project-URL: Repository, https://github.com/fair-wizard/fair-wizard-integration-sdk
Keywords: fair-wizard,integration,automation,sdk
Classifier: Development Status :: 5 - Production/Stable
Classifier: Programming Language :: Python
Classifier: Programming Language :: Python :: 3.11
Requires-Python: <4,>=3.11
License-File: LICENSE
Requires-Dist: pydantic
Requires-Dist: func-timeout
